odoo8_addon_website_mail_snippet_responsive-8.0.2.1.0.99.dev10-py3.8-nspkg.pth
odoo_addons/website_mail_snippet_responsive/README.rst
odoo_addons/website_mail_snippet_responsive/__init__.py
odoo_addons/website_mail_snippet_responsive/__openerp__.py
odoo_addons/website_mail_snippet_responsive/i18n/ar.po
odoo_addons/website_mail_snippet_responsive/i18n/bg.po
odoo_addons/website_mail_snippet_responsive/i18n/bs.po
odoo_addons/website_mail_snippet_responsive/i18n/ca.po
odoo_addons/website_mail_snippet_responsive/i18n/cs.po
odoo_addons/website_mail_snippet_responsive/i18n/da.po
odoo_addons/website_mail_snippet_responsive/i18n/de.po
odoo_addons/website_mail_snippet_responsive/i18n/el_GR.po
odoo_addons/website_mail_snippet_responsive/i18n/en_GB.po
odoo_addons/website_mail_snippet_responsive/i18n/es.po
odoo_addons/website_mail_snippet_responsive/i18n/es_AR.po
odoo_addons/website_mail_snippet_responsive/i18n/es_CL.po
odoo_addons/website_mail_snippet_responsive/i18n/es_CO.po
odoo_addons/website_mail_snippet_responsive/i18n/es_CR.po
odoo_addons/website_mail_snippet_responsive/i18n/es_DO.po
odoo_addons/website_mail_snippet_responsive/i18n/es_EC.po
odoo_addons/website_mail_snippet_responsive/i18n/es_MX.po
odoo_addons/website_mail_snippet_responsive/i18n/es_PE.po
odoo_addons/website_mail_snippet_responsive/i18n/es_PY.po
odoo_addons/website_mail_snippet_responsive/i18n/es_VE.po
odoo_addons/website_mail_snippet_responsive/i18n/et.po
odoo_addons/website_mail_snippet_responsive/i18n/fa.po
odoo_addons/website_mail_snippet_responsive/i18n/fi.po
odoo_addons/website_mail_snippet_responsive/i18n/fr.po
odoo_addons/website_mail_snippet_responsive/i18n/he.po
odoo_addons/website_mail_snippet_responsive/i18n/hr.po
odoo_addons/website_mail_snippet_responsive/i18n/hr_HR.po
odoo_addons/website_mail_snippet_responsive/i18n/hu.po
odoo_addons/website_mail_snippet_responsive/i18n/id.po
odoo_addons/website_mail_snippet_responsive/i18n/it.po
odoo_addons/website_mail_snippet_responsive/i18n/ja.po
odoo8_addon_website_mail_snippet_responsive-8.0.2.1.0.99.dev10.dist-info/METADATA
odoo8_addon_website_mail_snippet_responsive-8.0.2.1.0.99.dev10.dist-info/WHEEL
odoo8_addon_website_mail_snippet_responsive-8.0.2.1.0.99.dev10.dist-info/namespace_packages.txt
odoo8_addon_website_mail_snippet_responsive-8.0.2.1.0.99.dev10.dist-info/top_level.txt
odoo8_addon_website_mail_snippet_responsive-8.0.2.1.0.99.dev10.dist-info/RECORD
