Metadata-Version: 2.1
Name: odoo8-addon-website-mail-snippet-responsive
Version: 8.0.2.1.0.99.dev10
Summary: Well... pseudo-responsive (see description)
Home-page: http://www.antiun.com
Author: Antiun Ingeniería S.L., Odoo Community Association (OCA)
Author-email: support@odoo-community.org
License: AGPL-3
Platform: UNKNOWN
Classifier: Programming Language :: Python
Classifier: Framework :: Odoo
Classifier: Framework :: Odoo :: 8.0
Classifier: License :: OSI Approved :: GNU Affero General Public License v3
Requires-Python: ~=2.7
Requires-Dist: odoo8-addon-website-mail-snippet-vertical-resize-base
Requires-Dist: odoo (<9.0a,>=8.0a)
